{
  "id": "c59cc62f-299d-44d3-bced-8d94501f1380",
  "name": "FunBot",
  "description": "A simple and fun bot to get started with CSML!",
  "default_flow": "Hello",
  "tags": [],
  "flows": [
    {
      "name": "CatGifs",
      "description": "Show infinitely many fabulous cat gifs",
      "commands": [],
      "tags": []
    },
    {
      "name": "Hello",
      "description": "Tell your users what this bot is about!",
      "commands": [],
      "tags": []
    },
    {
      "name": "RandomJoke",
      "description": "Get random hilarious (or not) joke",
      "commands": [],
      "tags": []
    }
  ],
  "files": [],
  "functions": [],
  "apps": [
    {
      "name": "giphy",
      "description": "Find random GIFs and stickers relevant to your chatbot conversation. Powered by Giphy.",
      "args": [
        "action=\"gif|sticker\"",
        "query=\"\""
      ],
      "runtime": "nodejs12.x",
      "handler": "index.handler",
      "environment": {},
      "app_id": "7c8ce645-fb76-4d8f-ab47-90f4ffe3ca8a",
      "version": "1.1.0"
    }
  ]
}
